gitmeup/__init__.py
gitmeup/cli.py
gitmeup-1.0.2.dist-info/licenses/LICENSE
gitmeup-1.0.2.dist-info/METADATA
gitmeup-1.0.2.dist-info/WHEEL
gitmeup-1.0.2.dist-info/entry_points.txt
gitmeup-1.0.2.dist-info/top_level.txt
gitmeup-1.0.2.dist-info/RECORD
