Metadata-Version: 2.4
Name: gitmeup
Version: 1.0.2
Summary: LLM-assisted conventional commits generator for git repositories. Automatically generates git add and commit lines based on git diff and status.
License: DUAL LICENSE AGREEMENT
Project-URL: Homepage, https://github.com/ikramagix/gitmeup
Project-URL: Source, https://github.com/ikramagix/gitmeup
Project-URL: Issues, https://github.com/ikramagix/gitmeup/issues
Classifier: Programming Language :: Python :: 3
Classifier: Programming Language :: Python :: 3 :: Only
Classifier: Operating System :: OS Independent
Requires-Python: >=3.10
License-File: LICENSE
Requires-Dist: google-genai>=0.6.0
Requires-Dist: python-dotenv>=1.0.0
Dynamic: license-file
